backtracked/__init__.py
backtracked/utils.py
backtracked/client/__init__.py
backtracked/client/client.py
backtracked/client/constants.py
backtracked/client/http.py
backtracked/client/socket.py
backtracked/client/engine/packets.py
backtracked/models/__init__.py
backtracked/models/base.py
backtracked/models/errors.py
backtracked/models/message.py
backtracked/models/playlist.py
backtracked/models/room.py
backtracked/models/user.py
backtracked-0.1.1.dist-info/LICENSE.md
backtracked-0.1.1.dist-info/METADATA
backtracked-0.1.1.dist-info/WHEEL
backtracked-0.1.1.dist-info/top_level.txt
backtracked-0.1.1.dist-info/RECORD
