Metadata-Version: 2.1
Name: backtracked
Version: 0.1.1
Summary: Python & asyncio wrapper for the QueUp API
Home-page: https://github.com/hedgehog1029/backtracked
Author: offbeatwitch
Author-email: obw@generalprogramming.org
License: UNKNOWN
Project-URL: Bug Tracker, https://github.com/hedgehog1029/backtracked/issues
Project-URL: Documentation, https://backtracked.readthedocs.io/en/latest/
Platform: UNKNOWN
Classifier: Development Status :: 4 - Beta
Classifier: Programming Language :: Python :: 3.8
Classifier: License :: Free for non-commercial use
Classifier: Operating System :: OS Independent
Classifier: Intended Audience :: Developers
Classifier: Topic :: Internet
Classifier: Topic :: Software Development :: Libraries
Classifier: Topic :: Software Development :: Libraries :: Python Modules
Classifier: Framework :: AsyncIO
Classifier: Typing :: Typed
Requires-Python: >=3.8
Requires-Dist: aiohttp
